ormax/__init__.py
ormax/core.py
ormax/exceptions.py
ormax/fields.py
ormax/query.py
ormax/utils.py
ormax-1.2.1.dist-info/licenses/LICENSE
ormax-1.2.1.dist-info/METADATA
ormax-1.2.1.dist-info/WHEEL
ormax-1.2.1.dist-info/top_level.txt
ormax-1.2.1.dist-info/RECORD
