Metadata-Version: 2.4
Name: ormax
Version: 1.2.1
Summary: High-performance async ORM for all major databases
Home-page: https://github.com/shayanheidari01/ormax
Author: Shayan Heidari
Author-email: shayanheidari01@gmail.com
License: MIT
Project-URL: Bug Tracker, https://github.com/shayanheidari01/ormax/issues
Project-URL: Documentation, https://github.com/shayanheidari01/ormax#readme
Project-URL: Source Code, https://github.com/shayanheidari01/ormax
Keywords: orm,async,asyncio,database,sql,mysql,postgresql,sqlite,mariadb,database-orm,mssql,sqlserver,oracle,aurora
Classifier: Development Status :: 5 - Production/Stable
Classifier: Intended Audience :: Developers
Classifier: License :: OSI Approved :: MIT License
Classifier: Operating System :: OS Independent
Classifier: Programming Language :: Python :: 3
Classifier: Programming Language :: Python :: 3.7
Classifier: Programming Language :: Python :: 3.8
Classifier: Programming Language :: Python :: 3.9
Classifier: Programming Language :: Python :: 3.10
Classifier: Programming Language :: Python :: 3.11
Classifier: Programming Language :: Python :: 3 :: Only
Classifier: Topic :: Database
Classifier: Topic :: Software Development :: Libraries :: Python Modules
Classifier: Framework :: AsyncIO
Requires-Python: >=3.7
License-File: LICENSE
Provides-Extra: mysql
Requires-Dist: aiomysql>=0.1.14; extra == "mysql"
Provides-Extra: postgresql
Requires-Dist: asyncpg>=0.27.0; extra == "postgresql"
Provides-Extra: sqlite
Requires-Dist: aiosqlite>=0.19.0; extra == "sqlite"
Provides-Extra: mssql
Requires-Dist: aioodbc>=0.17.0; extra == "mssql"
Provides-Extra: oracle
Requires-Dist: async-oracledb>=1.0.0; extra == "oracle"
Provides-Extra: dev
Requires-Dist: pytest>=7.0.0; extra == "dev"
Requires-Dist: pytest-asyncio>=0.20.0; extra == "dev"
Requires-Dist: black>=22.0.0; extra == "dev"
Requires-Dist: flake8>=5.0.0; extra == "dev"
Requires-Dist: mypy>=0.950; extra == "dev"
Provides-Extra: all
Requires-Dist: aiomysql>=0.1.14; extra == "all"
Requires-Dist: asyncpg>=0.27.0; extra == "all"
Requires-Dist: aiosqlite>=0.19.0; extra == "all"
Requires-Dist: aioodbc>=0.17.0; extra == "all"
Requires-Dist: async-oracledb>=1.0.0; extra == "all"
Dynamic: author
Dynamic: author-email
Dynamic: classifier
Dynamic: description
Dynamic: description-content-type
Dynamic: home-page
Dynamic: keywords
Dynamic: license
Dynamic: license-file
Dynamic: project-url
Dynamic: provides-extra
Dynamic: requires-python
Dynamic: summary
